Pyjo/Base.py
Pyjo/Collection.py
Pyjo/Date.py
Pyjo/EventEmitter.py
Pyjo/Headers.py
Pyjo/HelloWorld.py
Pyjo/Loader.py
Pyjo/Log.py
Pyjo/Parameters.py
Pyjo/Path.py
Pyjo/Regexp.py
Pyjo/Test.py
Pyjo/URL.py
Pyjo/Upload.py
Pyjo/Util.py
Pyjo/__init__.py
Pyjo/Asset/File.py
Pyjo/Asset/Memory.py
Pyjo/Asset/__init__.py
Pyjo/Content/MultiPart.py
Pyjo/Content/Single.py
Pyjo/Content/__init__.py
Pyjo/Cookie/Request.py
Pyjo/Cookie/Response.py
Pyjo/Cookie/__init__.py
Pyjo/DOM/CSS.py
Pyjo/DOM/HTML.py
Pyjo/DOM/__init__.py
Pyjo/IOLoop/Client.py
Pyjo/IOLoop/Delay.py
Pyjo/IOLoop/Server.py
Pyjo/IOLoop/Stream.py
Pyjo/IOLoop/__init__.py
Pyjo/IOLoop/certs/server.crt
Pyjo/IOLoop/certs/server.key
Pyjo/JSON/Pointer.py
Pyjo/JSON/__init__.py
Pyjo/Message/Request.py
Pyjo/Message/Response.py
Pyjo/Message/__init__.py
Pyjo/Reactor/Base.py
Pyjo/Reactor/Poll.py
Pyjo/Reactor/Select.py
Pyjo/Reactor/__init__.py
Pyjo/Server/Base.py
Pyjo/Server/CGI.py
Pyjo/Server/Daemon.py
Pyjo/Server/WSGI.py
Pyjo/Server/__init__.py
Pyjo/String/Bytes.py
Pyjo/String/Mixin.py
Pyjo/String/Unicode.py
Pyjo/String/__init__.py
Pyjo/Transaction/HTTP.py
Pyjo/Transaction/WebSocket.py
Pyjo/Transaction/__init__.py
Pyjo/UserAgent/CookieJar.py
Pyjo/UserAgent/Proxy.py
Pyjo/UserAgent/Transactor.py
Pyjo/UserAgent/__init__.py
Pyjoyment/Base.py
Pyjoyment/Lite.py
Pyjoyment/__init__.py
Pyjoyment-0.0.1.dist-info/DESCRIPTION.rst
Pyjoyment-0.0.1.dist-info/METADATA
Pyjoyment-0.0.1.dist-info/RECORD
Pyjoyment-0.0.1.dist-info/WHEEL
Pyjoyment-0.0.1.dist-info/metadata.json
Pyjoyment-0.0.1.dist-info/top_level.txt
Pyjoyment-0.0.1.dist-info/zip-safe
