Metadata-Version: 2.0
Name: Pyjoyment
Version: 0.0.1
Summary: An asynchronous, event driver web framework for the Python programming language.
Home-page: http://github.com/dex4er/Pyjoyment
Author: Piotr Roszatycki
Author-email: piotr.roszatycki@gmail.com
License: Artistic
Download-URL: https://github.com/dex4er/Pyjoyment/archive/master.zip
Keywords: async framework html http mojo mojolicious pyjo pyjoyment tap test websocket wsgi
Platform: UNKNOWN
Classifier: Development Status :: 2 - Pre-Alpha
Classifier: Environment :: Web Environment
Classifier: Intended Audience :: Developers
Classifier: License :: OSI Approved :: Artistic License
Classifier: Operating System :: OS Independent
Classifier: Programming Language :: Python
Classifier: Programming Language :: Python :: 2.7
Classifier: Programming Language :: Python :: 3.3
Classifier: Programming Language :: Python :: 3.4
Classifier: Programming Language :: Python :: 3.5
Classifier: Topic :: Internet :: WWW/HTTP :: HTTP Servers
Classifier: Topic :: Internet :: WWW/HTTP :: WSGI :: Server
Classifier: Topic :: Software Development :: Testing
